src/__init__.py
src/cli.py
src/convert.py
src/version.py
uhabits_converter-0.3.0.dist-info/entry_points.txt
uhabits_converter-0.3.0.dist-info/LICENSE
uhabits_converter-0.3.0.dist-info/WHEEL
uhabits_converter-0.3.0.dist-info/METADATA
uhabits_converter-0.3.0.dist-info/RECORD
