Metadata-Version: 2.1
Name: uhabits-converter
Version: 0.3.0
Summary: convert types of habit from uhabits
Home-page: https://github.com/ConorSheehan1/uhabits_converter
License: MIT
Author: Conor Sheehan
Author-email: conor.sheehan.dev@gmail.com
Requires-Python: >=3.8
Classifier: Intended Audience :: End Users/Desktop 
Classifier: License :: OSI Approved :: MIT License
Classifier: Programming Language :: Python :: 3
Classifier: Programming Language :: Python :: 3.8
Classifier: Programming Language :: Python :: 3.9
Classifier: Programming Language :: Python :: 3.10
Classifier: Programming Language :: Python :: 3
Classifier: Topic :: Utilities
Requires-Dist: fire (>=0.4.0,<0.5.0)
Requires-Dist: inquirer (>=2.9.1,<3.0.0)
Requires-Dist: rich (>=11.2.0,<12.0.0); python_version >= "3.8" and python_version < "4.0"
